meltano/edk/__init__.py
meltano/edk/extension.py
meltano/edk/logging.py
meltano/edk/models.py
meltano/edk/process.py
meltano/edk/types.py
meltano/py.typed
meltano_edk-0.5.0.dist-info/LICENSE
meltano_edk-0.5.0.dist-info/METADATA
meltano_edk-0.5.0.dist-info/WHEEL
meltano_edk-0.5.0.dist-info/RECORD
