Metadata-Version: 2.1
Name: meltano.edk
Version: 0.5.0
Summary: A framework for building Meltano extensions
Home-page: https://meltano.com
License: Apache-2.0
Keywords: Meltano,Meltano Extension,Meltano EDK
Author: Meltano Team and Contributors
Maintainer: Meltano Team and Contributors
Requires-Python: >=3.9
Classifier: Intended Audience :: Developers
Classifier: License :: OSI Approved :: Apache Software License
Classifier: Operating System :: OS Independent
Classifier: Programming Language :: Python :: 3
Classifier: Programming Language :: Python :: 3.9
Classifier: Programming Language :: Python :: 3.10
Classifier: Programming Language :: Python :: 3.11
Classifier: Programming Language :: Python :: 3.12
Classifier: Programming Language :: Python :: 3.13
Classifier: Programming Language :: Python :: Implementation :: CPython
Classifier: Topic :: Software Development :: Libraries :: Application Frameworks
Classifier: Typing :: Typed
Provides-Extra: docs
Requires-Dist: PyYAML (>=6,<7)
Requires-Dist: devtools (>=0.9.0,<1)
Requires-Dist: furo (>=2022.12.7,<2025.0.0) ; extra == "docs"
Requires-Dist: myst-parser (>=0.17.2,<3.1.0) ; extra == "docs"
Requires-Dist: pydantic (>=2,<3)
Requires-Dist: sphinx (>=4.5,<9.0) ; extra == "docs"
Requires-Dist: sphinx-autobuild (>=2021.3.14,<2022.0.0) ; extra == "docs"
Requires-Dist: sphinx-copybutton (>=0.3.1,<0.6.0) ; extra == "docs"
Requires-Dist: structlog (>=21,<25)
Project-URL: Changelog, https://github.com/meltano/edk/blob/main/CHANGELOG.md
Project-URL: Issue Tracker, https://github.com/meltano/edk/issues
Project-URL: Repository, https://github.com/meltano/edk
Project-URL: Slack, https://meltano.com/slack
Project-URL: Twitter, https://twitter.com/meltanodata/
Project-URL: Youtube, https://www.youtube.com/meltano
